miro_api/__init__.py
miro_api/api/__init__.py
miro_api/api_client.py
miro_api/api_extended.py
miro_api/api_response.py
miro_api/configuration.py
miro_api/exceptions.py
miro_api/miro_api_wrapper.py
miro_api/models/__init__.py
miro_api/models/actor.py
miro_api/models/add_project_member_request.py
miro_api/models/admin_role.py
miro_api/models/app_card_create_request.py
miro_api/models/app_card_data.py
miro_api/models/app_card_data_changes.py
miro_api/models/app_card_data_platform.py
miro_api/models/app_card_data_response.py
miro_api/models/app_card_data_response_platform_bulk_create_operation_experimental_release_using_file_from_device.py
miro_api/models/app_card_data_response_platformcreateitemsinbulkusingfilefromdevice.py
miro_api/models/app_card_item.py
miro_api/models/app_card_style.py
miro_api/models/app_card_style_platform_bulk_create_operation_experimental_release.py
miro_api/models/app_card_style_platform_bulk_create_operation_experimental_release_using_file_from_device.py
miro_api/models/app_card_style_platformbulkcreateoperation.py
miro_api/models/app_card_style_platformcreateitemsinbulkusingfilefromdevice.py
miro_api/models/app_card_update_request.py
miro_api/models/attach_tag_to_item400_response.py
miro_api/models/audit_context.py
miro_api/models/audit_created_by.py
miro_api/models/audit_event.py
miro_api/models/audit_object.py
miro_api/models/audit_organization.py
miro_api/models/audit_page.py
miro_api/models/audit_team.py
miro_api/models/basic_error.py
miro_api/models/basic_error_organizations_enterprise_plan.py
miro_api/models/basic_error_teams_enterprise_plan.py
miro_api/models/board.py
miro_api/models/board_changes.py
miro_api/models/board_content_log_data.py
miro_api/models/board_data_classification_label.py
miro_api/models/board_export_job_id.py
miro_api/models/board_export_job_status.py
miro_api/models/board_export_result.py
miro_api/models/board_export_task_result.py
miro_api/models/board_item_content_log.py
miro_api/models/board_links.py
miro_api-2.2.3.dist-info/METADATA
miro_api-2.2.3.dist-info/WHEEL
miro_api-2.2.3.dist-info/RECORD
